nats_consumer/__init__.py
nats_consumer/apps.py
nats_consumer/client.py
nats_consumer/consumer.py
nats_consumer/exceptions.py
nats_consumer/management/commands/__init__.py
nats_consumer/management/commands/nats_consumer.py
nats_consumer/migrations.py
nats_consumer/operations.py
nats_consumer/settings.py
django_nats_consumer-1.2.0.dist-info/LICENSE
django_nats_consumer-1.2.0.dist-info/METADATA
django_nats_consumer-1.2.0.dist-info/WHEEL
django_nats_consumer-1.2.0.dist-info/RECORD
