Metadata-Version: 2.1
Name: django-nats-consumer
Version: 1.2.0
Summary: Django NATS Consumer
Home-page: https://github.com/dev360/django-nats-consumer
License: BSD-3-Clause
Keywords: django,nats,jetstream,consumer,async
Requires-Python: >=3.8
Classifier: Development Status :: 2 - Pre-Alpha
Classifier: Environment :: Web Environment
Classifier: Framework :: Django
Classifier: Intended Audience :: Developers
Classifier: License :: OSI Approved :: BSD License
Classifier: Operating System :: OS Independent
Classifier: Programming Language :: Python
Classifier: Programming Language :: Python :: 3
Classifier: Programming Language :: Python :: 3.8
Classifier: Programming Language :: Python :: 3.9
Classifier: Programming Language :: Python :: 3.10
Classifier: Programming Language :: Python :: 3.11
Classifier: Programming Language :: Python :: 3.12
Classifier: Programming Language :: Python :: 3.13
Requires-Dist: django (>=4.1)
Requires-Dist: nats-py (>=2.9.0)
Project-URL: Repository, https://github.com/dev360/django-nats-consumer
